[
  {
    "id": 1,
    "sentence": "目前，在变压器故障诊断中，单靠电气试验方法往往很难发现某些局部故障和发热缺陷，而通过变压器油中气体的色谱分析这种化学检测的方法，对发现变压器内部的某些潜伏性故障及其发展程度的早期诊断非常灵敏而有效，这已为大量故障诊断的实践所证明。",
    "cause-effect": [
      "电气试验方法局限,难以发现局部故障",
      "色谱分析方法优势,有效诊断潜伏故障"
    ]
  },
  {
    "id": 2,
    "sentence": "油色谱分析的原理是基于任何一种特定的烃类气体的产生速率随温度而变化，在特定温度下，往往有某一种气体的产气率会出现最大值;随着温度升高，产气率最大的气体依次为甲烷、乙烷、乙烯、乙炔。",
    "cause-effect": [
      "温度变化,特定气体产气率变化",
      "温度升高,产气率最大气体依次为甲烷",
      "温度升高,产气率最大气体依次为乙烷",
      "温度升高,产气率最大气体依次为乙烯",
      "温度升高,产气率最大气体依次为乙炔"
    ]
  },
  {
    "id": 3,
    "sentence": "而局部过热、电晕和电弧是导致油浸纸绝缘中产生故障特征气体的主要原因。",
    "cause-effect": [
      "局部过热,油浸纸绝缘产生故障特征气体",
      "电晕,油浸纸绝缘产生故障特征气体",
      "电弧,油浸纸绝缘产生故障特征气体"
    ]
  },
  {
    "id": 4,
    "sentence": "变压器在正常运行状态下，由于油和固体绝缘会逐渐老化、变质，分解出极少量的气体(主要包括氢、甲烷、乙烷、乙烯、乙炔、一氧化碳、二氧化碳等多种气体)。",
    "cause-effect": [
      "油和固体绝缘老化变质,分解出气体"
    ]
  },
  {
    "id": 5,
    "sentence": "当变压器内部发生过热性故障、放电性故障或内部绝缘受潮时，这些气体的含量会迅速增加。",
    "cause-effect": [
      "过热性故障,气体含量增加",
      "放电性故障,气体含量增加",
      "内部绝缘受潮,气体含量增加"
    ]
  },
  {
    "id": 6,
    "sentence": "故障类型：油过热：主要增大的――CH4、C2H4 次要增大的――H2、C2H6油纸过热:主要增大的――CH4、C2H4、CO、CO2 次要增大的――H2、C2H6油纸中局放:主要增大的――H2、CH4、C2H2、CO 次要增大的――C2H6、CO2油中火花放电：主要增大的――C2H2、H2油中电弧：主要增大的――H2、C2H2 次要增大的――CH4、C2H4、C2H6油纸中电弧:主要增大的――H2、C2H2、CO、CO2 次要增大的――CH4、C2H4、C2H6、受潮或油有气泡：主要增大的――H2油中气体的各种成分含量的多少和故障的性质及程度直接有关。",
    "cause-effect": [
      "油过热,CH4和C2H4主要增大",
      "油过热,H2和C2H6次要增大",
      "油纸过热,CH4、C2H4、CO和CO2主要增大",
      "油纸过热,H2和C2H6次要增大",
      "油纸中局放,H2、CH4、C2H2和CO主要增大",
      "油纸中局放,C2H6和CO2次要增大",
      "油中火花放电,C2H2和H2主要增大",
      "油中电弧,H2和C2H2主要增大",
      "油中电弧,CH4、C2H4和C2H6次要增大",
      "油纸中电弧,H2、C2H2、CO和CO2主要增大",
      "油纸中电弧,CH4、C2H4、C2H6、受潮或油有气泡次要增大",
      "气体成分含量变化,故障性质及程度判断"
    ]
  },
  {
    "id": 7,
    "sentence": "因此在设备运行过程中，定期测量溶解于油中的气体成分和含量，对于及早发现充油电力设备内部存在的潜伏性故障有非常重要的意义和现实的成效。",
    "cause-effect": [
      "定期测量气体成分和含量,及早发现潜伏性故障"
    ]
  },
  {
    "id": 8,
    "sentence": "过热性故障：分接开关接触不良占、铁芯多点接地和局部短路或漏磁环流、导线过热和接头不良或紧固件松动引起过热、其余、为其他故障，如局部油道堵塞，致使局部散热不良而造成的过热性故障。",
    "cause-effect": [
      "分接开关接触不良,过热性故障",
      "铁芯多点接地,过热性故障",
      "局部短路或漏磁环流,过热性故障",
      "导线过热和接头不良或紧固件松动,过热性故障",
      "局部油道堵塞,局部散热不良",
      "局部散热不良,过热性故障"
    ]
  },
  {
    "id": 9,
    "sentence": "根据色谱分析数据进行变压器内部故障诊断时，应包括：(1)分析气体产生的原因及变化。",
    "cause-effect": [
      "气体产生的原因,气体变化"
    ]
  },
  {
    "id": 10,
    "sentence": "若需加强监视，则应缩短周期。",
    "cause-effect": [
      "加强监视,缩短周期"
    ]
  },
  {
    "id": 11,
    "sentence": "变压器无论是热故障还是电故障，最终都将导致绝缘介质裂解产生各种特征气体。",
    "cause-effect": [
      "热故障,绝缘介质裂解",
      "电故障,绝缘介质裂解",
      "绝缘介质裂解,产生特征气体"
    ]
  },
  {
    "id": 12,
    "sentence": "由于碳氢键之间的键能低，生成热小，在绝缘的分解过程中，一般总是先生成H2，因此H2是各种故障特征气体的主要组成成分之一。",
    "cause-effect": [
      "碳氢键键能低,生成热小",
      "生成热小,H2生成",
      "H2生成,H2成为特征气体成分"
    ]
  },
  {
    "id": 13,
    "sentence": "变压器内部进水受潮是一种内部潜伏性故障，其特征气体H2含量很高。",
    "cause-effect": [
      "变压器内部进水受潮,H2含量很高"
    ]
  },
  {
    "id": 14,
    "sentence": "客观上如果色谱分析发现H2含量超标，而其他成分并没有增加时，可大致先判断为设备含有水分，为进一步判别，可做油中微水含量分析。",
    "cause-effect": [
      "色谱分析H2超标,判断设备含水分",
      "设备含水分,进行油中微水分析"
    ]
  },
  {
    "id": 15,
    "sentence": "导致水分分解出H2有两种可能：一是水分和铁产生化学反应;二是在高电场作用下水本身分子分解。",
    "cause-effect": [
      "水分和铁产生化学反应,水分解出H2",
      "高电场作用,水分子分解"
    ]
  },
  {
    "id": 16,
    "sentence": "设备受潮时固体绝缘材料含水量比油中含水量要大100多倍，而H2含量高，大多是由于油、纸绝缘内含有气体和水分，所以在现场处理设备受潮时，仅靠采用真空滤油法不能持久地降低设备中的含水量，原因在于真空滤油对于设备整体的水分影响不大。",
    "cause-effect": [
      "设备受潮,固体绝缘材料含水量大",
      "油、纸绝缘含有气体和水分,H2含量高",
      "采用真空滤油法,不能持久降低含水量",
      "真空滤油对整体水分影响不大,无法有效除水"
    ]
  },
  {
    "id": 17,
    "sentence": "另外，还有一种误判断的情况，是气相色谱仪发生异常，，因分离柱长期使用，特别是用振荡脱气法脱气吸附了油，当吸附达到一定程度，便在一定条件下释放出来，使分析发生误差。",
    "cause-effect": [
      "分离柱长期使用,吸附油",
      "吸附油达到一定程度,释放油",
      "油释放,分析误差"
    ]
  },
  {
    "id": 18,
    "sentence": "(2)乙炔变化乙炔的产生与放电性故障有关，当变压器内部发生电弧放电时，C2H2一般占总烃的20-70%，H2占氢烃总量的30-90%，并且在绝大多数情况下，C2H4含量高于CH4。",
    "cause-effect": [
      "电弧放电,乙炔产生",
      "电弧放电,氢气产生",
      "电弧放电,C2H4含量高于CH4"
    ]
  },
  {
    "id": 19,
    "sentence": "当C2H2含量占主要成分且超标时，则很可能是设备绕组短路或分接开关切换产生弧光放电所致。",
    "cause-effect": [
      "C2H2含量超标,设备绕组短路",
      "C2H2含量超标,分接开关切换产生弧光放电"
    ]
  },
  {
    "id": 20,
    "sentence": "如果其他成分没超标，而C2H2超标且增长速率较快，则可能是设备内部存在高能量放电故障。",
    "cause-effect": [
      "C2H2超标且增长速率较快,设备内部存在高能量放电故障"
    ]
  },
  {
    "id": 21,
    "sentence": "在过热性故障中，当只有热源处的绝缘油分解时，特征气体甲烷和乙烯两者之和一般可占总烃的80%以上，且随着故障点温度的升高，C2H4所占比例也增加。",
    "cause-effect": [
      "过热性故障,绝缘油分解",
      "绝缘油分解,甲烷和乙烯含量增加",
      "故障点温度升高,C2H4比例增加"
    ]
  },
  {
    "id": 22,
    "sentence": "另外，丁腈橡胶材料在变压器油中将可能产生大量的CH4，丁腈在变压器油中产生甲烷的本质是橡胶将本身所含的CH4释放到油中，而不是将油催化裂介为CH4。",
    "cause-effect": [
      "丁腈橡胶材料在变压器油中,产生大量CH4",
      "橡胶释放本身所含CH4,CH4进入油中"
    ]
  },
  {
    "id": 23,
    "sentence": "硫化丁腈橡胶在油中释放CH4的主要成分是硫化剂，其次是增塑剂、硬脂酸等含甲基的物质，而释放量取决于硫化条件。",
    "cause-effect": [
      "硫化剂在油中存在,释放CH4",
      "增塑剂含甲基,释放CH4",
      "硬脂酸含甲基,释放CH4",
      "硫化条件变化,释放量变化"
    ]
  },
  {
    "id": 24,
    "sentence": "无论何种放电形式，除了产生氢烃类气体外，与过热故障一样，只要有固体绝缘介入，都会产生CO和CO2。",
    "cause-effect": [
      "固体绝缘介入,产生CO和CO2"
    ]
  },
  {
    "id": 25,
    "sentence": "但从总体上来说，过热性故障的产气速率比放电性故障慢。",
    "cause-effect": [
      "过热性故障,产气速率慢"
    ]
  },
  {
    "id": 26,
    "sentence": "《变压器油中溶解气体分析和判断导则》中也只对CO含量正常值提出了参考意见：开放式变压器CO含量的正常值一般应在300ppm以下，若总烃含量超过150ppm，CO含量超过300ppm,则设备有可能存在固体绝缘过热性故障;若CO含量虽超过300ppm，但总烃含量在正常范围，可认为正常。",
    "cause-effect": [
      "总烃含量超过150ppm且CO含量超过300ppm,设备可能存在固体绝缘过热性故障",
      "CO含量超过300ppm但总烃含量正常,可认为设备正常"
    ]
  },
  {
    "id": 27,
    "sentence": "密封式变压器，溶于油中的CO含量一般均高于开放式变压器，其正常值约800ppm，但在突发性绝缘击穿故障中，CO、CO2含量不一定高，因此其含量变化常被人们忽视。",
    "cause-effect": [
      "密封式变压器,油中CO含量高",
      "CO含量变化,被人们忽视"
    ]
  },
  {
    "id": 28,
    "sentence": "由于CO、CO2气体含量的变化反映了设备内部绝缘材料老化或故障，而固体绝缘材料决定了充油设备的寿命。",
    "cause-effect": [
      "CO、CO2气体含量变化,反映绝缘材料老化或故障",
      "固体绝缘材料状态,决定充油设备寿命"
    ]
  },
  {
    "id": 29,
    "sentence": "因此必须重视绝缘油中CO、CO2含量的变化。",
    "cause-effect": [
      "重视绝缘油中CO、CO2含量的变化,因此"
    ]
  },
  {
    "id": 30,
    "sentence": "正常运行中的设备内部绝缘油和固体绝缘材料由于受到电场、热度、湿度及氧的作用，随运行时间而发生速度缓慢的老化现象，除产生一些非气态的劣化产物外，还会产生少量的氧、低分子烃类气体和碳的氧化物等，其中碳的氧化物CO、CO2含量最高。",
    "cause-effect": [
      "电场、热度、湿度及氧的作用,绝缘材料老化",
      "绝缘材料老化,产生劣化产物",
      "绝缘材料老化,产生氧、低分子烃类气体和碳的氧化物"
    ]
  },
  {
    "id": 31,
    "sentence": "变压器正常运行下产生的CO、CO2含量随设备的运行年限的增加而上升，这种变化趋势较缓慢，说明变压器内固体绝缘材料逐渐老化，随着老化程度的加剧，一方面绝缘材料强度不断降低，有被击穿的可能;另一方面绝缘材料老化产生沉积物，降低绝缘油的性能，易造成局部过热或其它故障。",
    "cause-effect": [
      "变压器正常运行,CO、CO2含量上升",
      "CO、CO2含量上升,绝缘材料逐渐老化",
      "绝缘材料老化,绝缘强度降低",
      "绝缘材料老化,产生沉积物",
      "沉积物产生,绝缘油性能下降",
      "绝缘油性能下降,局部过热",
      "绝缘油性能下降,其它故障"
    ]
  },
  {
    "id": 32,
    "sentence": "这说明设备内部绝缘材料老化发展到一定程度有可能产生剧烈变化，容易形成设备故障或损坏事故。",
    "cause-effect": [
      "绝缘材料老化,设备故障",
      "绝缘材料老化,设备损坏"
    ]
  },
  {
    "id": 33,
    "sentence": "因此在进行色谱分析判断设备状况时，CO、CO2作为固体绝缘材料有关的特征气体，当其含量上升到一定程度或其含量变化幅度较大时，都应引起警惕，尽早将绝缘老化严重的设备退出运行，以防发生击穿短路事故。",
    "cause-effect": [
      "CO、CO2含量上升,绝缘老化严重",
      "绝缘老化严重,击穿短路事故"
    ]
  },
  {
    "id": 34,
    "sentence": "固体绝缘材料在高能量电弧放电时产生较多的CO、CO2由于电弧放电的能量密度高，在电应力作用下会产生高速电子流，固体绝缘材料遭受这些电子轰击后，将受到严重破坏，同时，产生的大量气体一方面会进一步降低绝缘，另一方面还含有较多的可燃气体，因此若不及时处理，严重时有可能造成设备的重大损坏或爆炸事故。",
    "cause-effect": [
      "电弧放电能量密度高,产生高速电子流",
      "高速电子流轰击绝缘材料,绝缘材料严重破坏",
      "电子轰击产生大量气体,绝缘性能进一步降低",
      "气体含有可燃气体,存在爆炸风险",
      "绝缘降低和可燃气体,设备重大损坏或爆炸"
    ]
  },
  {
    "id": 35,
    "sentence": "当设备内部发生各种过热性故障时，由于局部温度较高，可导致热点附近的绝缘物发生热分解而析出气体，变压器内油浸绝缘纸开始热解时产生的主要气体是CO2，随温度的升高，产生的CO含量也增多，使CO与CO2比值升高，至800度时，比值可高达2.5。",
    "cause-effect": [
      "局部温度较高,绝缘物热分解析出气体",
      "绝缘物热分解,CO含量增多",
      "CO含量增多,CO与CO2比值升高"
    ]
  },
  {
    "id": 36,
    "sentence": "局部过热危害不如放电故障那样严重，但从发展的后果分析，热点可加速绝缘物的老化、分解，产生各种气体，低温热点发展成为高温热点，附近的绝缘物被破坏，导致故障扩大。",
    "cause-effect": [
      "热点,绝缘物老化",
      "热点,产生气体",
      "低温热点,高温热点",
      "绝缘物破坏,故障扩大"
    ]
  },
  {
    "id": 37,
    "sentence": "充油设备中固体绝缘受热分解时，变压器油中所溶解的CO、CO2浓度就会偏高。",
    "cause-effect": [
      "固体绝缘受热分解,CO、CO2浓度偏高"
    ]
  },
  {
    "id": 38,
    "sentence": "CO、CO2的产生与设备内部固体绝缘材料的老化或故障有明显的关系，反映了设备的绝缘状况。",
    "cause-effect": [
      "CO、CO2产生,绝缘材料老化或故障"
    ]
  },
  {
    "id": 39,
    "sentence": "当C2H2含量较大时，往往表现为绝缘介质内部存在严重的局部放电故障，同时常伴有电弧烧伤与过热，因此会出现C2H2含量明显增大，且占总烃较大比例的情况。",
    "cause-effect": [
      "C2H2含量较大,绝缘介质内部存在局部放电故障",
      "局部放电故障,伴有电弧烧伤与过热",
      "电弧烧伤与过热,C2H2含量明显增大",
      "电弧烧伤与过热,C2H2占总烃较大比例"
    ]
  },
  {
    "id": 40,
    "sentence": "因为这可能存在着由低能放电发展成高能放电的危险。",
    "cause-effect": [
      "低能放电,高能放电"
    ]
  },
  {
    "id": 41,
    "sentence": "过热涉及固体绝缘时，除了产生上述气体之外，还会产生大量的CO和CO2当电气设备内部存在接触不良时，如分接开关接触不良、连接部分松动、绝缘不良，特征气体会明显增加。",
    "cause-effect": [
      "过热涉及固体绝缘,产生CO和CO2",
      "接触不良,特征气体增加",
      "分接开关接触不良,特征气体增加",
      "连接部分松动,特征气体增加",
      "绝缘不良,特征气体增加"
    ]
  },
  {
    "id": 42,
    "sentence": "当总烃含量超过正常值，计算!C2H2/C2H4的比值小于0.1时为过热性故障，大于0.1时为放电性故障。",
    "cause-effect": [
      "总烃含量超过正常值且C2H2/C2H4比值小于0.1,过热性故障",
      "总烃含量超过正常值且C2H2/C2H4比值大于0.1,放电性故障"
    ]
  },
  {
    "id": 43,
    "sentence": "计算C2H4/C2H6的比值可确定其故障性质，当比值小于1时一般为低温过热，比值大于1而小于3时，为中温过热，大于3时为高温过热故障。",
    "cause-effect": [
      "C2H4/C2H6比值小于1,低温过热",
      "C2H4/C2H6比值大于1小于3,中温过热",
      "C2H4/C2H6比值大于3,高温过热故障"
    ]
  },
  {
    "id": 44,
    "sentence": "而计算CH4/H2的比值可确定是纯放电还是放电兼过热故障，比值小于1为放电故障，大于1为放电兼过热故障。",
    "cause-effect": [
      "CH4/H2比值小于1,判断为放电故障",
      "CH4/H2比值大于1,判断为放电兼过热故障"
    ]
  },
  {
    "id": 45,
    "sentence": "如果故障在导电回路，往往产有C2H2，且含量较高，C2H4/C2H6比值也较高，C2H4的产气速率往往高于CH4的产气速率。",
    "cause-effect": [
      "故障在导电回路,C2H2含量较高",
      "故障在导电回路,C2H4/C2H6比值较高",
      "C2H4产气速率高,CH4产气速率低"
    ]
  },
  {
    "id": 46,
    "sentence": "计算CO和CO2的比值，可判断固体绝缘中的含水量，含水量大时，CO/CO2比值小。",
    "cause-effect": [
      "含水量大,CO/CO2比值小"
    ]
  },
  {
    "id": 47,
    "sentence": "故障温度高且时间长时，CO/CO2比值大。",
    "cause-effect": [
      "温度高且时间长,CO/CO2比值大"
    ]
  },
  {
    "id": 48,
    "sentence": "而严重故障时，生成的CO来不及溶解而导致故障，这在CO/CO2的比值上得不到反映。",
    "cause-effect": [
      "严重故障,生成的CO来不及溶解"
    ]
  },
  {
    "id": 49,
    "sentence": "IEC导则推荐以CO/CO2比值作为判据，认为该比值大于0.33或小于0.99时，很可能有纤维绝缘分解故障。",
    "cause-effect": [
      "CO/CO2比值大于0.33或小于0.99,纤维绝缘分解故障"
    ]
  },
  {
    "id": 50,
    "sentence": "通过计算C2H2/C2H4、CH4/H2、C2H4/C2H6，将选用的5种特征气体构成三对比值，在相同的情况下将这些比值以不同的编码表示，根据测试结果计算得出编码，并把三对比值换算成对应的编码组，然后查表对应得出故障类型和故障的性质，但该法所给编码组并不全，给实际分析工作带来诸多不便。",
    "cause-effect": [
      "编码组不全,分析工作不便"
    ]
  },
  {
    "id": 51,
    "sentence": "应用三比值法应当注意的问题：1)对油中各种气体含量正常的变压器，其比值没有意义。",
    "cause-effect": [
      "油中气体含量正常,比值无意义"
    ]
  },
  {
    "id": 52,
    "sentence": "如果不论变压器是否存在故障，一律使用三比值法，就有可能将正常的变压器误判断为故障变压器，造成不必要的经济损失。",
    "cause-effect": [
      "不区分变压器状态使用三比值法,误判变压器故障",
      "误判变压器故障,造成经济损失"
    ]
  },
  {
    "id": 53,
    "sentence": "3)由于每一种故障对应于一组比值，所以对多种故障的变压器，可能找不到相对应的比值组合。",
    "cause-effect": [
      "每一种故障对应一组比值,多种故障的变压器可能找不到对应的比值组合"
    ]
  },
  {
    "id": 54,
    "sentence": "由于三比值法还未能包括和反映变压器内部故障的所有形态，所以它还在发展及积累经验之中，有时可结合其他的一些比值判断方法综合分析，如一种四比值法在实际应用中也取得一定的效果。",
    "cause-effect": [
      "三比值法未涵盖所有故障形态,方法仍在发展中"
    ]
  },
  {
    "id": 55,
    "sentence": "但在实际应用中往往难以求得，因而多采用相对产气速率分析判断。",
    "cause-effect": [
      "难以求得,采用相对产气速率分析判断"
    ]
  },
  {
    "id": 56,
    "sentence": "当设备经过真空滤油脱气后，宜及时作好绝对产气速率的测量，并根据有关建议利用如下判断标准：1)总烃的绝对值小于注意值、总烃产气速率小于注意值，则变压器正常。",
    "cause-effect": [
      "真空滤油脱气,需测量产气速率",
      "总烃绝对值小于注意值,变压器正常",
      "总烃产气速率小于注意值,变压器正常"
    ]
  },
  {
    "id": 57,
    "sentence": "2)总烃大于注意值、但不超过注意值的3倍，总烃产气速率小于注意值，则变压器有故障，但发展缓慢，可继续运行并注意观察。",
    "cause-effect": [
      "总烃大于注意值且产气速率小于注意值,变压器有故障",
      "变压器有故障,发展缓慢",
      "变压器有故障,可继续运行并注意观察"
    ]
  },
  {
    "id": 58,
    "sentence": "3)总烃大于注意值、但不超过注意值的3倍，总烃产气速率为注意值的1-2倍，则变压器有故障，应缩短试验周期，密切注意故障发展。",
    "cause-effect": [
      "总烃大于注意值且产气速率为注意值的1-2倍,变压器有故障",
      "变压器有故障,应缩短试验周期",
      "变压器有故障,密切注意故障发展"
    ]
  },
  {
    "id": 59,
    "sentence": "4)总烃大于注意值的3倍，总烃产气速率大于注意值的3倍，则设备有严重故障，发展迅速，应立即采取必要的措施，有条件时可进行吊罩检修。",
    "cause-effect": [
      "总烃大于注意值3倍,设备有严重故障",
      "总烃产气速率大于注意值3倍,设备有严重故障",
      "设备有严重故障,应立即采取必要措施"
    ]
  },
  {
    "id": 60,
    "sentence": "(六)根据总烃变化趋势(总烃随时间的变化曲线)判断对大量过热性故障变压器的色谱试验分析结果表明，变压器内部存在潜伏性故障时，总烃在随时间的变化曲线上主要有两种表现形式：一种是总烃与时间大致成正比增长关系;另一种是总烃随时间变化没有明显的递增关系，而是出现时增时减的现象。",
    "cause-effect": [
      "变压器内部潜伏性故障,总烃变化呈现两种形式"
    ]
  },
  {
    "id": 61,
    "sentence": "对于第一种曲线，过热常常会从低温逐步发展成为高温，甚至有的迅速发展为电弧放电而造成变压器损坏事故。",
    "cause-effect": [
      "过热,高温",
      "高温,电弧放电",
      "电弧放电,变压器损坏"
    ]
  },
  {
    "id": 62,
    "sentence": "因此，对这种故障应及时采取措施。",
    "cause-effect": [
      "故障,应及时采取措施"
    ]
  },
  {
    "id": 63,
    "sentence": "变压器内部存在高能量放电性故障时，宜根据故障的发展情况来决定检修时间。",
    "cause-effect": [
      "高能量放电性故障,决定检修时间"
    ]
  },
  {
    "id": 64,
    "sentence": "如果近期内没有条件，应缩短色谱分析周期，追踪分析，密切注视故障的发展趋势。",
    "cause-effect": [
      "近期无条件,缩短色谱分析周期"
    ]
  },
  {
    "id": 65,
    "sentence": "故障类型属于过热性的变压器，宜根据电压等级、故障程度、故障发展速度和油中气体的饱和程度来决定维修时间。",
    "cause-effect": [
      "过热性故障,维修时间确定"
    ]
  },
  {
    "id": 66,
    "sentence": "对于500kV变压器，只要总烃量达到注意值的2倍，常认为应停运进行检修，这是因为500kV变压器内部场强高;如果气体含量大、产气量多，油中可能产生气泡，有被击穿的可能性，所以不能仅以气体饱和水平来决定维修时间。",
    "cause-effect": [
      "总烃量达到注意值的2倍,应停运进行检修",
      "500kV变压器内部场强高,应停运进行检修",
      "气体含量大、产气量多,油中可能产生气泡",
      "油中产生气泡,有被击穿的可能性",
      "气体含量大、产气量多,不能仅以气体饱和水平来决定维修时间"
    ]
  },
  {
    "id": 67,
    "sentence": "(七)特征气体变化与变压器内部故障的关系特征气体变化与变压器内部故障的关系，主要特征气体故障类型主要特征气体故障类型:H2高，总烃不高，CH4为总烃的主要成分，有微量C2H2--油中电晕(火花放电时总烃高)C2H2高，总烃和H2较高，C2H2位总烃的主要成分――高温电弧放电总烃及H2较高，但C2H2位构成总烃的主要成分――高温热点或局部高温过热C2H4、H2、CO、CO2及总烃均较高――绝缘局部过热或固体绝缘散热不良总烃高，H2和C2H2均较高――油中裸金属过热并有电弧放电，固体绝缘损伤总烃不高，H2>100,CH4占总烃主要成分――局部放电产生的特征气体常见故障为：引线焊接不良，开关接触不良，导线有毛刺，引线有短路，绕组匝间、层间有短路，铁芯穿心螺杆短路或有多点接地，局部过热等。",
    "cause-effect": [
      "H2高，总烃不高，CH4为总烃的主要成分，有微量C2H2,油中电晕",
      "C2H2高，总烃和H2较高，C2H2为总烃的主要成分,高温电弧放电",
      "总烃及H2较高，但C2H2为构成总烃的主要成分,高温热点或局部高温过热",
      "C2H4、H2、CO、CO2及总烃均较高,绝缘局部过热或固体绝缘散热不良",
      "总烃高，H2和C2H2均较高,油中裸金属过热并有电弧放电",
      "总烃不高，H2>100，CH4占总烃主要成分,局部放电产生的特征气体",
      "引线焊接不良,变压器内部故障",
      "开关接触不良,变压器内部故障",
      "导线有毛刺,变压器内部故障",
      "引线有短路,变压器内部故障",
      "绕组匝间层间短路,变压器内部故障",
      "铁芯穿心螺杆短路或多点接地,变压器内部故障",
      "局部过热,变压器内部故障"
    ]
  },
  {
    "id": 68,
    "sentence": "此外，与油中溶解气体相类似，判断变压器内部故障的方法，是用气体继电器积聚的气体来判断。",
    "cause-effect": [
      "用气体继电器积聚的气体,判断变压器内部故障"
    ]
  },
  {
    "id": 69,
    "sentence": "不过，它只有在变压器内部已有故障时才能判断，而不能发现早期潜伏性故障。",
    "cause-effect": [
      "变压器内部故障,才能判断"
    ]
  },
  {
    "id": 70,
    "sentence": "这种方法通常是以气体继电器中的气体颜色和故障性质的关系来判断变压器内部故障。",
    "cause-effect": [
      "气体颜色,故障性质判断"
    ]
  }
]