{
  "id": "26cd54db-ff45-48d2-bd7f-f53c2171cf93",
  "created_time": "2025-11-15 15:38:34",
  "name": "我们来一步一步分析给",
  "reason_paths": [
    "变压器内发出异响<-绕组松动或变形"
  ],
  "summary": "我们来一步一步分析给定的因果推理链，并结合变压器运行与故障诊断的专业知识，找出故障的**根本原因**。\n\n---\n\n### 给定因果链：\n> **变压器内发出异响 ← 绕组松动或变形**\n\n这个因果关系表示：**变压器内部出现异响**，其直接原因是**绕组发生了松动或变形**。\n\n---\n\n### 第一步：分析“变压器内发出异响”的可能来源\n\n变压器在正常运行时会发出均匀的电磁噪声（即“嗡嗡”声），但如果出现**异常声响**（如噼啪声、放电声、强烈振动声、金属撞击声等），则通常表明内部存在故障。常见原因包括：\n\n- 绕组松动或变形\n- 铁心多点接地或松动\n- 内部放电（局部放电或电弧）\n- 分接开关接触不良\n- 夹件或结构件松动\n\n但在本题中，已明确指出异响的原因是“绕组松动或变形”，所以我们聚焦于这一条路径。\n\n---\n\n### 第二步：分析“绕组松动或变形”的成因\n\n绕组是变压器的核心部件之一，设计上应具备足够的机械强度以承受电磁力和热应力。绕组发生松动或变形，通常不是偶然现象，而是由以下一种或多种因素导致：\n\n1. **短路电流冲击**（最常见）  \n   - 变压器在运行中若遭遇出口短路或近区短路，会产生巨大的电动力（遵循 $ F \\propto I^2 $），可能导致绕组径向变形（鼓包）或轴向位移（扭曲）。  \n   - 这种机械损伤会使绕组支撑结构失效，产生松动，在运行中因电磁振动而发出异响。\n\n2. **制造或装配缺陷**  \n   - 绕组绕制不紧、垫块分布不均、压紧装置预紧力不足等制造工艺问题，会导致绕组在长期运行中逐渐松动。\n\n3. **运输或安装过程中的机械冲击**  \n   - 若变压器在运输途中遭受剧烈震动或撞击，可能导致内部绕组位移或支撑结构损坏。\n\n4. **长期过载或热老化**  \n   - 长期高温运行会使绝缘材料（如纸板、撑条）老化、收缩或碳化，失去支撑作用，进而导致绕组松动。\n\n5. **多次短路冲击累积损伤**  \n   - 即使未发生严重短路，多次小电流短路冲击也可能造成疲劳损伤，逐步引起绕组变形。\n\n---\n\n### 第三步：追溯根本原因（Root Cause）\n\n虽然“绕组松动或变形”是异响的直接原因，但它本身通常是**次生故障**，需要进一步追问：**什么导致了绕组松动或变形？**\n\n结合电力系统实际运行经验，**最常见的根本原因是：**\n\n> ✅ **变压器曾遭受外部短路电流冲击**\n\n这种情况下，强大的电磁力破坏了绕组的机械稳定性，即使保护迅速动作切除故障，瞬时电动力仍可能造成不可逆的机械形变。\n\n此外，如果变压器投运时间较短，且无短路记录，则需考虑**制造或运输缺陷**作为根本原因。\n\n但根据一般统计，在运行中的变压器出现绕组变形，**约70%以上与短路冲击有关**。\n\n---\n\n### 结论：根本原因分析\n\n**故障现象**：变压器内发出异响  \n↓  \n**直接原因**：绕组松动或变形  \n↓  \n**根本原因**：**变压器曾遭受外部短路电流冲击**（最可能）  \n（或：制造/运输过程中造成的机械损伤 —— 若无短路历史）\n\n---\n\n### 建议措施：\n\n1. **调取故障录波数据**，确认是否发生过出口短路；\n2. **进行绕组变形测试**（如频率响应法FRA或低电压阻抗法），判断绕组是否变形；\n3. **检查历史负载与跳闸记录**；\n4. 如确认绕组受损，应尽快安排停电检修或更换；\n5. 加强近区短路防护（如加装限流电抗器、快速断路器等）。\n\n---\n\n✅ **最终结论：**\n> 该变压器发出异响的根本原因是 **绕组松动或变形**，而其深层/根本诱因极有可能是 **变压器曾经历外部短路电流冲击**，导致绕组机械结构受损。"
}