{
  "id": "cc605ba9-9377-4def-9d0c-78391d76e080",
  "created_time": "2025-11-16 17:18:30",
  "name": "根据提供的因果推理链",
  "reason_paths": [
    "变压器异常<-过负荷运行"
  ],
  "summary": "根据提供的因果推理链：  \n**[变压器异常 ← 过负荷运行]**\n\n我们可以逐步进行因果逻辑分析如下：\n\n---\n\n### 第一步：明确终端现象  \n**“变压器异常”** 是当前观察到的现象。  \n在变压器运行中，“异常”可能表现为温度升高、油中气体含量异常（如总烃超标）、噪声增大、绝缘性能下降等。这些异常通常通过在线监测系统或定期试验（如油色谱分析）被发现。\n\n---\n\n### 第二步：追溯直接原因  \n根据因果链，**“过负荷运行”** 是导致“变压器异常”的直接原因。\n\n- **过负荷运行** 指的是变压器长期或短期承受超过其额定容量的负载。\n- 后果包括：\n  - 绕组温度显著升高；\n  - 加剧绝缘材料老化；\n  - 可能引发局部过热，导致油裂解产生可燃气体（如甲烷、乙烯等）；\n  - 增加机械应力，可能导致绕组变形。\n\n因此，**过负荷运行足以引发多种类型的变压器异常**，尤其是热性故障。\n\n---\n\n### 第三步：深入挖掘根本原因（Root Cause）  \n虽然“过负荷运行”是直接原因，但我们需要进一步思考：**为什么会发生过负荷运行？**\n\n结合电力系统运行经验，可能的根本原因包括：\n\n1. **系统负荷增长超出设计预期**  \n   - 区域用电需求增加，变电站未及时扩容。\n\n2. **运行方式安排不当**  \n   - 在N-1条件下，其他变压器停运，导致本台变压器被迫长期过载。\n\n3. **保护或监控系统失效**  \n   - 负荷监控缺失或报警功能失灵，未能及时采取措施。\n\n4. **设备选型不当（初始设计问题）**  \n   - 变压器额定容量偏小，无法满足实际运行需求。\n\n5. **调度管理不善或应急响应滞后**  \n   - 发现过负荷后未及时转移负荷或限制用电。\n\n---\n\n### 结论：根本原因分析\n\n> 在当前因果链仅提供“变压器异常 ← 过负荷运行”的前提下，**“过负荷运行”是已知最深层的原因**。  \n> 因此，在现有信息范围内，**过负荷运行即为本次故障的根本原因**。\n\n但需强调：若要实现更深层次的根因治理，建议进一步调查以下方面：\n\n✅ 历史负荷曲线是否显示持续超载？  \n✅ 是否存在设计或规划缺陷？  \n✅ 运行维护和调度策略是否合理？\n\n---\n\n### 建议措施：\n\n1. **加强负荷监测与预警机制**，设置合理的过负荷报警阈值；\n2. **优化电网运行方式**，避免长时间过载运行；\n3. **开展变压器热稳定性评估**，必要时进行增容改造；\n4. **定期进行油色谱分析和红外测温**，及时发现潜在热故障；\n5. **完善应急预案**，确保在重载情况下能快速响应。\n\n---\n\n### 总结：\n\n🔹 **故障现象**：变压器异常  \n🔹 **直接原因**：过负荷运行  \n🔹 **根本原因（基于当前因果链）**：**过负荷运行**\n\n> ⚠️ 注：若后续调查揭示“过负荷”本身由其他因素引起（如设计不足、调度失误），则根本原因应向上追溯至管理或规划层面。当前数据下，以“过负荷运行”为根本原因最为合理。"
}