{
  "id": "ebc3f462-591d-4fb2-b552-b828aea2d383",
  "created_time": "2025-12-01 09:34:06",
  "name": "我们来逐步分析给定的",
  "reason_paths": [
    "变压器不存在放电现象<-乙炔含量为0ppm"
  ],
  "summary": "我们来逐步分析给定的因果推理链，并结合变压器故障诊断的专业知识，找出故障的根本原因。\n\n---\n\n### **给定的因果推理链：**\n\n> **变压器不存在放电现象 ← 乙炔含量为0ppm**\n\n这个表达式表示：“**变压器不存在放电现象**”的原因是“**乙炔含量为0ppm**”。\n\n我们按因果逻辑进行逆向推理（从结果追溯到根本原因），并结合油中溶解气体分析（DGA, Dissolved Gas Analysis）的原理进行解读。\n\n---\n\n### **第一步：理解乙炔（C₂H₂）在变压器故障诊断中的意义**\n\n在变压器油中溶解气体分析（DGA）中，**乙炔（C₂H₂）是一种关键特征气体**，其存在与否及浓度高低对判断故障类型具有重要意义：\n\n- **乙炔（C₂H₂）主要产生于高温电弧放电**（温度通常 > 1000°C）。\n- 典型的产生场景包括：\n  - 绕组间闪络\n  - 引线对地放电\n  - 分接开关拉弧\n  - 严重的接触不良导致电弧\n- 因此，**乙炔的存在是放电性故障（尤其是电弧放电）的重要标志**。\n- 相反，**乙炔含量为0ppm或极低（低于检测限）时，通常认为不存在明显的电弧放电现象**。\n\n---\n\n### **第二步：分析因果链的逻辑关系**\n\n> **变压器不存在放电现象 ← 乙炔含量为0ppm**\n\n这表示：由于油中未检测到乙炔（即乙炔 = 0ppm），因此可以推断变压器当前**没有发生电弧放电类故障**。\n\n这是一个基于DGA的合理推论。\n\n但注意：**乙炔为0ppm只能说明没有电弧放电，不能完全排除所有类型的放电**。例如：\n- **局部放电**（PD）在初期可能只产生氢气（H₂）和少量甲烷（CH₄），不一定生成乙炔。\n- 因此，严格来说，“无乙炔”不能100%排除所有放电，但可排除**高能量电弧放电**。\n\n但在工程实践中，若乙炔长期为0ppm，且其他气体无异常，通常认为**不存在显著的放电性故障**。\n\n---\n\n### **第三步：寻找根本原因**\n\n现在问题是：我们要找的是“变压器故障”的根本原因。  \n然而，在当前因果链中：\n\n- 并没有指出变压器**发生了故障**；\n- 相反，该链条表明：**不存在放电现象**（即一种潜在故障模式被排除）；\n- 支持这一结论的依据是：**乙炔含量为0ppm**。\n\n因此，这条因果链实际上是一个**否定性诊断结论**：  \n👉 **目前没有证据支持变压器存在电弧放电类故障**。\n\n---\n\n### **结论与根本原因分析**\n\n#### ✅ 结论：\n- 根据所提供的因果推理链，**无法识别出变压器存在明确的故障**；\n- 相反，该链条用于**排除一种特定类型的严重故障——电弧放电**；\n- 因此，**不存在由电弧放电引起的变压器故障**。\n\n#### ❓ 是否存在其他故障？\n- 本链条未提供关于其他气体（如H₂、CH₄、C₂H₄、CO等）的信息；\n- 也无法判断是否存在过热、受潮、机械振动等问题；\n- 所以不能完全排除所有故障类型，仅能针对“放电”做出判断。\n\n#### 🎯 根本原因分析：\n> 在当前信息下，**变压器并未表现出放电故障的迹象**，其根本原因是：\n>\n> 🔹 **未检测到乙炔（C₂H₂ = 0ppm）**，  \n> 表明系统中**没有足以产生乙炔的高温电弧过程**，  \n> 进而说明：**设备运行正常，或至少不存在高能量放电故障源**。\n\n---\n\n### ✅ 最终回答：\n\n根据提供的因果推理链 “变压器不存在放电现象 ← 乙炔含量为0ppm”，结合变压器故障诊断知识分析如下：\n\n1. 乙炔（C₂H₂）是电弧放电的特征气体，其含量为0ppm表明未发生高温电弧放电；\n2. 因此，可以合理推断变压器当前**不存在放电性故障**；\n3. 该因果链的本质是**排除性诊断**，而非定位故障；\n4. 在现有信息下，**变压器无放电故障的根本原因是：未检测到乙炔，说明缺乏产生电弧的能量源或故障条件**；\n5. 建议结合其他气体成分（如H₂、CO、总烃等）和电气试验进一步综合判断整体健康状态。\n\n> ⚠️ 注意：若用户怀疑变压器存在故障，但乙炔为0ppm，则应考虑非放电类故障，如：\n> - 低温过热（<300°C）\n> - 绝缘受潮\n> - 铁芯多点接地\n> - 机械松动等\n\n请提供更多数据（如全部DGA结果、电气试验、运行工况）以便更全面的根本原因分析。"
}